pydantic_ai_blocking_approval/__init__.py
pydantic_ai_blocking_approval/py.typed
pydantic_ai_blocking_approval/toolset.py
pydantic_ai_blocking_approval/types.py
pydantic_ai_blocking_approval-0.9.0.dist-info/METADATA
pydantic_ai_blocking_approval-0.9.0.dist-info/WHEEL
pydantic_ai_blocking_approval-0.9.0.dist-info/licenses/LICENSE
pydantic_ai_blocking_approval-0.9.0.dist-info/RECORD
