Metadata-Version: 2.4
Name: pydantic-ai-blocking-approval
Version: 0.9.0
Summary: Synchronous, blocking approval system for PydanticAI agent tools
Project-URL: Homepage, https://github.com/zby/pydantic-ai-blocking-approval
Project-URL: Repository, https://github.com/zby/pydantic-ai-blocking-approval
Author: Zbigniew Łukasiak
License-Expression: MIT
License-File: LICENSE
Keywords: agent,approval,hitl,human-in-the-loop,llm,pydantic-ai,tools
Classifier: Development Status :: 3 - Alpha
Classifier: Intended Audience :: Developers
Classifier: License :: OSI Approved :: MIT License
Classifier: Programming Language :: Python :: 3
Classifier: Programming Language :: Python :: 3.10
Classifier: Programming Language :: Python :: 3.11
Classifier: Programming Language :: Python :: 3.12
Classifier: Programming Language :: Python :: 3.13
Classifier: Programming Language :: Python :: 3.14
Classifier: Topic :: Software Development :: Libraries :: Python Modules
Classifier: Typing :: Typed
Requires-Python: >=3.10
Requires-Dist: pydantic-ai>=0.1
Requires-Dist: pydantic>=2.0
Provides-Extra: dev
Requires-Dist: pytest-asyncio>=0.21; extra == 'dev'
Requires-Dist: pytest>=7.0; extra == 'dev'
